and_otp_uri.py
and_otp_uri-0.0.2.dist-info/METADATA
and_otp_uri-0.0.2.dist-info/WHEEL
and_otp_uri-0.0.2.dist-info/entry_points.txt
and_otp_uri-0.0.2.dist-info/top_level.txt
and_otp_uri-0.0.2.dist-info/RECORD
