Metadata-Version: 2.1
Name: and-otp-uri
Version: 0.0.2
Summary: Convert andOTP or GNOME Authenticator backups into otpauth-URIs
Project-URL: Repository, https://gitlab.com/zvyn/and-otp-uri
Requires-Python: >=3.11
